LAB1/mux_21.v
module mux_2to1(
mux_out, din_0, din_1, sel
);

input din_0, din_1,sel;

output mux_out;

wire w_not1, w_and1, w_and2;

not not1(w_not1, sel);
and and1(w_and1, w_not1, din_0);
and and2(w_and2, sel, din_1);
or or1(mux_out, w_and1, w_and2);

endmodule

LAB1/stimulus.v
module stimulus;
    reg sel;
    reg din_0, din_1;
    wire mux_out;

    mux_2to1 mux1(mux_out, din_0, din_1, sel);

    initial
        begin
            $dumpfile("MuxTimeDiagram.vcd");
            $dumpvars(0,stimulus);
            din_0 = 1'b0;
            din_1 = 1'b1;
            sel = 1'b0;
        end
    always
        #5 sel = ~sel;

    initial
    begin
        #100 $finish;
    end
    initial
        $monitor ($time, "d1=%d d2=%d sel=%d mux=%d", din_0,din_1,sel,mux_out);

endmodule

LAB1/MuxTimeDiagram.vcd
$date
	Mon Nov 06 23:13:00 2017
$end
$version
	Icarus Verilog
$end
$timescale
	1s
$end
$scope module stimulus $end
$var wire 1 ! mux_out $end
$var reg 1 " din_0 $end
$var reg 1 # din_1 $end
$var reg 1 $ sel $end
$scope module mux1 $end
$var wire 1 " din_0 $end
$var wire 1 # din_1 $end
$var wire 1 ! mux_out $end
$var wire 1 $ sel $end
$var wire 1 % w_and1 $end
$var wire 1 & w_and2 $end
$var wire 1 ' w_not1 $end
$upscope $end
$upscope $end
$enddefinitions $end
#0
$dumpvars
1'
0&
0%
0$
1#
0"
0!
$end
#5
1!
0'
1&
1$
#10
0!
1'
0&
0$
#15
1!
0'
1&
1$
#20
0!
1'
0&
0$
#25
1!
0'
1&
1$
#30
0!
1'
0&
0$
#35
1!
0'
1&
1$
#40
0!
1'
0&
0$
#45
1!
0'
1&
1$
#50
0!
1'
0&
0$
#55
1!
0'
1&
1$
#60
0!
1'
0&
0$
#65
1!
0'
1&
1$
#70
0!
1'
0&
0$
#75
1!
0'
1&
1$
#80
0!
1'
0&
0$
#85
1!
0'
1&
1$
#90
0!
1'
0&
0$
#95
1!
0'
1&
1$
#100
0!
1'
0&
0$
