LAB1/SRLatch.v
module SR_Latch(
     Q, QN, R, S
);

input R, S;

output Q, QN;

nor nor1(Q, R, QN);
nor nor2(QN, S, Q);

endmodule

LAB1/SRLatchStimulus.v
module SRLatchStimulus;
    reg S, R;
    wire Q, QN;

    SR_Latch sr_latch1(Q, QN, R, S);

    initial
        begin
          $dumpfile("SRTime.vcd");
          $dumpvars(0,SRLatchStimulus);
          S = 1'b0;
          R = 1'b0;
        end

    initial
      begin
        #5 S = 1'b1;
        #5 S = 1'b0;
        #5 R = 1'b1;
        #5 R = 1'b0;
        #5 S = 1'b1;
        #5 S = 1'b0; R = 1'b1;
        #5 S = 1'b1;
        #5 S = 1'b0; R = 1'b0;
      end

    initial
    begin
      #45 $finish;
    end

    initial
        $monitor($time, "S=%d R=%d Q=%d QN=%d", S, R, Q, QN);

endmodule

LAB1/SRTime.vcd
$date
	Mon Nov 06 23:13:17 2017
$end
$version
	Icarus Verilog
$end
$timescale
	1s
$end
$scope module SRLatchStimulus $end
$var wire 1 ! QN $end
$var wire 1 " Q $end
$var reg 1 # R $end
$var reg 1 $ S $end
$scope module sr_latch1 $end
$var wire 1 " Q $end
$var wire 1 ! QN $end
$var wire 1 # R $end
$var wire 1 $ S $end
$upscope $end
$upscope $end
$enddefinitions $end
#0
$dumpvars
0$
0#
x"
x!
$end
#5
1"
0!
1$
#10
0$
#15
1!
0"
1#
#20
0#
#25
1"
0!
1$
#30
1!
0"
1#
0$
#35
0!
1$
#40
1!
0#
0$
